aleat1/__init__.py
aleat1-0.0.1.dist-info/LICENSE
aleat1-0.0.1.dist-info/METADATA
aleat1-0.0.1.dist-info/WHEEL
aleat1-0.0.1.dist-info/top_level.txt
aleat1-0.0.1.dist-info/RECORD
