Metadata-Version: 2.1
Name: aleat1
Version: 0.0.1
Summary: An aleatory syntaxes package. Original generation.
Home-page: https://github.com
Author: Diego Ramirez
Author-email: dr01191115@gmail.com
License: UNKNOWN
Platform: UNKNOWN
Classifier: Programming Language :: Python :: 3
Classifier: License :: OSI Approved :: MIT License
Classifier: Operating System :: OS Independent
Requires-Python: >=3.7
